itcsmsgwclient/__init__.py
itcsmsgwclient/itcsmsgwclient.py
itcsmsgwclient/itcsmsgwclienttest.py
itcsmsgwclient-1.0.1.dist-info/DESCRIPTION.rst
itcsmsgwclient-1.0.1.dist-info/METADATA
itcsmsgwclient-1.0.1.dist-info/RECORD
itcsmsgwclient-1.0.1.dist-info/WHEEL
itcsmsgwclient-1.0.1.dist-info/metadata.json
itcsmsgwclient-1.0.1.dist-info/top_level.txt
