Metadata-Version: 2.0
Name: itcsmsgwclient
Version: 1.0.1
Summary: Python client module for the Intelecom Group AS SMS gateway
Home-page: https://github.com/Intelecom/smsgw-client-python
Author: Intelecom Group AS
Author-email: support.interactive@intele.com
License: MIT
Keywords: intelecom sms gateway
Platform: UNKNOWN
Classifier: Development Status :: 3 - Alpha
Classifier: Intended Audience :: Developers
Classifier: Topic :: Software Development :: Build Tools
Classifier: License :: OSI Approved :: MIT License
Classifier: Programming Language :: Python :: 2
Classifier: Programming Language :: Python :: 2.6
Classifier: Programming Language :: Python :: 2.7
Classifier: Programming Language :: Python :: 3
Classifier: Programming Language :: Python :: 3.2
Classifier: Programming Language :: Python :: 3.3
Classifier: Programming Language :: Python :: 3.4
Requires-Dist: jsonpickle
Requires-Dist: requests
Requires-Dist: requests-mock
Requires-Dist: six
